django_iseries/__init__.py
django_iseries/base.py
django_iseries/client.py
django_iseries/compiler.py
django_iseries/creation.py
django_iseries/introspection.py
django_iseries/operations.py
django_iseries/pybase.py
django_iseries/query.py
django_iseries/schemaEditor.py
django_iseries-1.0.6.dist-info/LICENSE
django_iseries-1.0.6.dist-info/WHEEL
django_iseries-1.0.6.dist-info/METADATA
django_iseries-1.0.6.dist-info/RECORD
